pip_inside/__init__.py
pip_inside/main.py
pip_inside/commands/__init__.py
pip_inside/commands/add.py
pip_inside/commands/build.py
pip_inside/commands/deps.py
pip_inside/commands/export.py
pip_inside/commands/init.py
pip_inside/commands/install.py
pip_inside/commands/publish.py
pip_inside/commands/remove.py
pip_inside/commands/shell.py
pip_inside/commands/upgrade.py
pip_inside/commands/version.py
pip_inside/commands/resources/.dockerignore
pip_inside/commands/resources/.gitignore
pip_inside/utils/__init__.py
pip_inside/utils/dependencies.py
pip_inside/utils/licenses.py
pip_inside/utils/markers.py
pip_inside/utils/misc.py
pip_inside/utils/packages.py
pip_inside/utils/pyproject.py
pip_inside/utils/spinner.py
pip_inside/utils/versions.py
pip_inside/utils/licenses/Apache-2.0.txt
pip_inside/utils/licenses/GPL-3.0-or-later.txt
pip_inside/utils/licenses/LGPL-3.0-or-later.txt
pip_inside/utils/licenses/MIT.txt
pip_inside/utils/licenses/MulanPSL-2.0.txt
pip_inside-0.2.11.dist-info/entry_points.txt
pip_inside-0.2.11.dist-info/LICENSE
pip_inside-0.2.11.dist-info/WHEEL
pip_inside-0.2.11.dist-info/METADATA
pip_inside-0.2.11.dist-info/RECORD
