Metadata-Version: 2.1
Name: pip_inside
Version: 0.2.11
Summary: Like poetry, but it's pip
Home-page: https://github.com/orctom/pip-inside
License: Apache-2.0
Author: orctom
Author-email: orctom <orctom@gmail.com>
Requires-Python: >=3.8
Classifier: Intended Audience :: Developers
Classifier: Programming Language :: Python :: 3
Classifier: Topic :: Software Development :: Libraries :: Python Modules
Requires-Dist: flit_core>=3.8.0
Requires-Dist: tomlkit
Requires-Dist: requests>=2.31.0
Requires-Dist: certifi>=2024.7.4
Requires-Dist: urllib3>=1.26.18
Requires-Dist: click
Requires-Dist: inquirerpy
Requires-Dist: pexpect
Requires-Dist: packaging
Requires-Dist: ruff ; extra == "dev"
Requires-Dist: passlib[bcrypt] ; extra == "dev"
Project-URL: homepage, https://github.com/orctom/pip-inside
Project-URL: repository, https://github.com/orctom/pip-inside
Provides-Extra: dev
